wexample_filestate_flutter-0.0.15.dist-info/METADATA
wexample_filestate_flutter-0.0.15.dist-info/WHEEL
wexample_filestate_flutter-0.0.15.dist-info/entry_points.txt
wexample_filestate_flutter/__init__.py
wexample_filestate_flutter/config_option/__init__.py
wexample_filestate_flutter/config_option/dart_format_config_option.py
wexample_filestate_flutter/config_value/__init__.py
wexample_filestate_flutter/config_value/flutter_config_value.py
wexample_filestate_flutter/const/__init__.py
wexample_filestate_flutter/const/flutter_file.py
wexample_filestate_flutter/file/__init__.py
wexample_filestate_flutter/file/flutter_file.py
wexample_filestate_flutter/option/__init__.py
wexample_filestate_flutter/option/flutter/__init__.py
wexample_filestate_flutter/option/flutter/abstract_flutter_file_content_option.py
wexample_filestate_flutter/option/flutter/dart_format_option.py
wexample_filestate_flutter/option/flutter_option.py
wexample_filestate_flutter/options_provider/__init__.py
wexample_filestate_flutter/options_provider/flutter_options_provider.py
wexample_filestate_flutter/py.typed
wexample_filestate_flutter/resources/__init__.py
wexample_filestate_flutter/resources/docker/Dockerfile.flutter-option
wexample_filestate_flutter/resources/docker/__init__.py
wexample_filestate_flutter/resources/docker/analysis_options.yaml
wexample_filestate_flutter-0.0.15.dist-info/RECORD
