Metadata-Version: 2.1
Name: wexample-filestate-flutter
Version: 0.0.15
Author-Email: weeger <contact@wexample.com>
License: MIT
Classifier: Programming Language :: Python :: 3
Classifier: License :: OSI Approved :: MIT License
Classifier: Operating System :: OS Independent
Requires-Python: >=3.10
Requires-Dist: attrs>=23.1.0
Requires-Dist: cattrs>=23.1.0
Requires-Dist: wexample-filestate==0.0.74
Provides-Extra: dev
Requires-Dist: pytest; extra == "dev"
Requires-Dist: pytest-cov; extra == "dev"
